README.md
pyproject.toml
setup.py
src/libcpuid/__init__.py
src/libcpuid/_ffi_build.py
src/libcpuid/_ffi_build_rtd.py
src/libcpuid/_ffi_build_utils.py
src/libcpuid/_utils.py
src/libcpuid/clock.py
src/libcpuid/enums.py
src/libcpuid/errors.py
src/libcpuid/info.py
src/libcpuid/msr.py
src/libcpuid/raw.py
src/libcpuid/sgx.py
src/libcpuid.egg-info/PKG-INFO
src/libcpuid.egg-info/SOURCES.txt
src/libcpuid.egg-info/dependency_links.txt
src/libcpuid.egg-info/requires.txt
src/libcpuid.egg-info/top_level.txt