Metadata-Version: 2.1
Name: libcpuid
Version: 0.1.0
Summary: Python bindings for the libcpuid C library
Author-email: Pavol Žáčik <zacikpa@gmail.com>
License: BSD-3-Clause
Requires-Dist: cffi
